AUTHORS
LICENSE
MANIFEST.in
README.rst
setup.py
django_easy_thumbnails_colorprofile.egg-info/PKG-INFO
django_easy_thumbnails_colorprofile.egg-info/SOURCES.txt
django_easy_thumbnails_colorprofile.egg-info/dependency_links.txt
django_easy_thumbnails_colorprofile.egg-info/requires.txt
django_easy_thumbnails_colorprofile.egg-info/top_level.txt
easy_thumbnails_colorprofile/__init__.py
easy_thumbnails_colorprofile/models.py
easy_thumbnails_colorprofile/thumbnail_processors.py