Metadata-Version: 1.1
Name: django-easy-thumbnails-colorprofile
Version: 0.5.1
Summary: A color profile converter for easy_thumbnails
Home-page: http://v.licheni.net/drc/django-easy-thumbnails-colorprofile.git
Author: Davide Riccardo Caliendo
Author-email: davide.licheni.net
License: GPLv3 License
Platform: UNKNOWN
Classifier: Environment :: Web Environment
Classifier: Framework :: Django
Classifier: Intended Audience :: Developers
Classifier: License :: OSI Approved :: GNU General Public License v3 (GPLv3)
Classifier: Operating System :: OS Independent
Classifier: Programming Language :: Python
Classifier: Programming Language :: Python :: 2.6
Classifier: Programming Language :: Python :: 2.7
Classifier: Topic :: Internet :: WWW/HTTP
Classifier: Topic :: Internet :: WWW/HTTP :: Dynamic Content
